{
    "mobileBottomRow": 26,
    "widgetName": "Divider1",
    "thickness": "2",
    "displayName": "Divider",
    "iconSVG": "/static/media/icon.3b7d47d7bd70da418a827287042cbb7f.svg",
    "searchTags": ["line"],
    "topRow": 34,
    "bottomRow": 38,
    "parentRowSpace": 10,
    "type": "DIVIDER_WIDGET",
    "capType": "nc",
    "hideCard": false,
    "mobileRightColumn": 59,
    "animateLoading": true,
    "parentColumnSpace": 8.65625,
    "dynamicTriggerPathList": [],
    "leftColumn": 0,
    "dynamicBindingPathList": [],
    "key": "2cmqoo1p5j",
    "dividerColor": "#ebebeb",
    "orientation": "horizontal",
    "strokeStyle": "solid",
    "isDeprecated": false,
    "rightColumn": 63,
    "widgetId": "q7itaeoph3",
    "capSide": 0,
    "minWidth": 450,
    "isVisible": true,
    "version": 1,
    "parentId": "f11n7r2acz",
    "tags": ["Layout"],
    "renderMode": "CANVAS",
    "isLoading": false,
    "mobileTopRow": 22,
    "responsiveBehavior": "fill",
    "originalTopRow": 38,
    "mobileLeftColumn": 39,
    "originalBottomRow": 42
}